Metadata-Version: 1.1
Name: Flask-Triangle
Version: 0.5.2
Summary: Integration of AngularJS and Flask.
Home-page: https://github.com/morgan-del/flask-triangle
Author: Morgan Delahaye-Prat
Author-email: mdp@m-del.fr
License: BSD
Platform: any
Classifier: Development Status :: 4 - Beta
Classifier: Environment :: Web Environment
Classifier: Intended Audience :: Developers
Classifier: License :: OSI Approved :: BSD License
Classifier: Operating System :: OS Independent
Classifier: Programming Language :: Python
Classifier: Topic :: Internet :: WWW/HTTP :: Dynamic Content
Classifier: Topic :: Software Development :: Libraries :: Python Modules
